fetchsep/__init__.py
fetchsep/cli.py
fetchsep/idsep/__init__.py
fetchsep/idsep/idsep.py
fetchsep/idsep/make_event_list.py
fetchsep/json/__init__.py
fetchsep/json/ccmc_json_handler.py
fetchsep/json/keys.py
fetchsep/json/read_json_example.py
fetchsep/json/templates/__init__.py
fetchsep/json/templates/model_example.json
fetchsep/json/templates/model_template.json
fetchsep/json/templates/observations_example.json
fetchsep/json/templates/observations_template.json
fetchsep/json/templates/triggers_template.json
fetchsep/opsep/__init__.py
fetchsep/opsep/batch_run_opsep.py
fetchsep/opsep/opsep.py
fetchsep/utils/__init__.py
fetchsep/utils/config.py
fetchsep/utils/date_handler.py
fetchsep/utils/define_background_idsep.py
fetchsep/utils/derive_background_opsep.py
fetchsep/utils/fetchsep.cfg
fetchsep/utils/move_output.py
fetchsep/utils/plotting_tools.py
fetchsep/utils/read_datasets.py
fetchsep-0.3.1.data/scripts/fetchsep_prepare_obs
fetchsep-0.3.1.data/scripts/idsep
fetchsep-0.3.1.data/scripts/make_opsep_event_list
fetchsep-0.3.1.data/scripts/opsep
fetchsep-0.3.1.data/scripts/opsep_batch
fetchsep-0.3.1.dist-info/AUTHORS.rst
fetchsep-0.3.1.dist-info/LICENSE
fetchsep-0.3.1.dist-info/METADATA
fetchsep-0.3.1.dist-info/WHEEL
fetchsep-0.3.1.dist-info/top_level.txt
fetchsep-0.3.1.dist-info/RECORD
