Metadata-Version: 2.1
Name: fetchsep
Version: 0.3.1
Summary: Identify SEP elevations above background in a time series (idsep) and analyze events individually (opsep)
Home-page: https://github.com/ktindiana/fetchsep
Author: Kathryn Whitman
Author-email: kathryn.whitman@nasa.gov
License: MIT license
Keywords: fetchsep
Classifier: Development Status :: 2 - Pre-Alpha
Classifier: Intended Audience :: Developers
Classifier: License :: OSI Approved :: MIT License
Classifier: Natural Language :: English
Classifier: Programming Language :: Python :: 3
Classifier: Programming Language :: Python :: 3.8
Classifier: Programming Language :: Python :: 3.9
Classifier: Programming Language :: Python :: 3.10
Requires-Python: >=3.8
License-File: LICENSE
License-File: AUTHORS.rst
Requires-Dist: astropy
Requires-Dist: python-dateutil
Requires-Dist: matplotlib
Requires-Dist: numpy
Requires-Dist: scipy
Requires-Dist: pandas
Requires-Dist: wget
Requires-Dist: zulu
Requires-Dist: lmfit
Requires-Dist: cycler
Requires-Dist: scikit-learn
Requires-Dist: seaborn
Requires-Dist: netCDF4
